finres_ggpt2_matplotlib/__init__.py
finres_ggpt2_matplotlib/test.py
finres_ggpt2_matplotlib/theme.py
finres_ggpt2_matplotlib/fonts/Poppins-Black.ttf
finres_ggpt2_matplotlib/fonts/Poppins-BlackItalic.ttf
finres_ggpt2_matplotlib/fonts/Poppins-Bold.ttf
finres_ggpt2_matplotlib/fonts/Poppins-BoldItalic.ttf
finres_ggpt2_matplotlib/fonts/Poppins-ExtraBold.ttf
finres_ggpt2_matplotlib/fonts/Poppins-ExtraBoldItalic.ttf
finres_ggpt2_matplotlib/fonts/Poppins-ExtraLight.ttf
finres_ggpt2_matplotlib/fonts/Poppins-ExtraLightItalic.ttf
finres_ggpt2_matplotlib/fonts/Poppins-Italic.ttf
finres_ggpt2_matplotlib/fonts/Poppins-Light.ttf
finres_ggpt2_matplotlib/fonts/Poppins-LightItalic.ttf
finres_ggpt2_matplotlib/fonts/Poppins-Medium.ttf
finres_ggpt2_matplotlib/fonts/Poppins-MediumItalic.ttf
finres_ggpt2_matplotlib/fonts/Poppins-Regular.ttf
finres_ggpt2_matplotlib/fonts/Poppins-SemiBold.ttf
finres_ggpt2_matplotlib/fonts/Poppins-SemiBoldItalic.ttf
finres_ggpt2_matplotlib/fonts/Poppins-Thin.ttf
finres_ggpt2_matplotlib/fonts/Poppins-ThinItalic.ttf
finres_ggpt2_matplotlib-0.5.0.dist-info/LICENSE
finres_ggpt2_matplotlib-0.5.0.dist-info/METADATA
finres_ggpt2_matplotlib-0.5.0.dist-info/WHEEL
finres_ggpt2_matplotlib-0.5.0.dist-info/entry_points.txt
finres_ggpt2_matplotlib-0.5.0.dist-info/top_level.txt
finres_ggpt2_matplotlib-0.5.0.dist-info/RECORD
