Metadata-Version: 2.1
Name: finres_ggpt2_matplotlib
Version: 0.5.0
Summary: A custom Matplotlib theme using the Poppins font styled like ggplot.
Home-page: https://github.com/yourusername/finres_ggpt2_matplotlib
Author: Vhiny
Author-email: vhiny.mombo@finres.dev
Project-URL: Bug Tracker, https://github.com/yourusername/finres_ggpt2_matplotlib/issues
Project-URL: Documentation, https://github.com/yourusername/finres_ggpt2_matplotlib/wiki
Project-URL: Source Code, https://github.com/yourusername/finres_ggpt2_matplotlib
Keywords: matplotlib theme poppins ggplot
Classifier: Programming Language :: Python :: 3
Classifier: License :: OSI Approved :: MIT License
Classifier: Operating System :: OS Independent
Classifier: Framework :: Matplotlib
Classifier: Topic :: Software Development :: Libraries :: Python Modules
Classifier: Intended Audience :: Developers
Requires-Python: >=3.6
License-File: LICENSE
Requires-Dist: matplotlib >=3.1.0
Requires-Dist: seaborn >=0.10.0
Provides-Extra: dev
Requires-Dist: pytest >=6.0 ; extra == 'dev'
Requires-Dist: twine ; extra == 'dev'
Requires-Dist: wheel ; extra == 'dev'
